{
  "match": [
    {
      "match_name": "IND/NEZ",
      "stadium": "SAHARA",
      "date": "2018-12-12",
      "id": 1
    }
  ],
  "teams": [
    {
      "match_id": 1,
      "team_name": "INDIA",
      "id": 1516871697
    },
    {
      "match_id": 1,
      "team_name": "NEWZLAND",
      "id": 1516871698
    }
  ],
  "players": [
    {
      "player_name": "SACHIN",
      "id": 1516872097,
      "team_id": 1516871697,
      "match_id": 1,
      "six": [
        {
          "x": 173.5,
          "y": 83
        },
        {
          "x": 227.5,
          "y": 65
        },
        {
          "x": 250.5,
          "y": 55
        },
        {
          "x": 319.5,
          "y": 37
        },
        {
          "x": 378.5,
          "y": 29
        },
        {
          "x": 385.5,
          "y": 29
        },
        {
          "x": 217.5,
          "y": 880
        },
        {
          "x": 527.5,
          "y": 880
        },
        {
          "x": 551.5,
          "y": 868
        },
        {
          "x": 626.5,
          "y": 857
        },
        {
          "x": 650.5,
          "y": 852
        }
      ],
      "four": [],
      "three": [],
      "one": []
    },
    {
      "player_name": "GANGULY",
      "id": 1516872297,
      "match_id": 1,
      "team_id": 1516871697,
      "six": [],
      "four": [],
      "three": [],
      "one": [
        {
          "x": 349.5,
          "y": 275
        },
        {
          "x": 387.5,
          "y": 256
        },
        {
          "x": 419.5,
          "y": 247
        },
        {
          "x": 426.5,
          "y": 245
        },
        {
          "x": 453.5,
          "y": 238
        },
        {
          "x": 461.5,
          "y": 247
        },
        {
          "x": 478.5,
          "y": 280
        },
        {
          "x": 496.5,
          "y": 320
        },
        {
          "x": 512.5,
          "y": 344
        },
        {
          "x": 525.5,
          "y": 366
        },
        {
          "x": 533.5,
          "y": 376
        }
      ]
    },
    {
      "player_name": "DRAVID",
      "id": 1516872197,
      "match_id": 1,
      "team_id": 1516871697,
      "six": [],
      "four": [
        {
          "x": 330.5,
          "y": 50
        },
        {
          "x": 378.5,
          "y": 36
        },
        {
          "x": 410.5,
          "y": 41
        },
        {
          "x": 490.5,
          "y": 65
        },
        {
          "x": 527.5,
          "y": 74
        },
        {
          "x": 550.5,
          "y": 83
        },
        {
          "x": 559.5,
          "y": 91
        },
        {
          "x": 599.5,
          "y": 120
        },
        {
          "x": 635.5,
          "y": 135
        },
        {
          "x": 676.5,
          "y": 180
        },
        {
          "x": 710.5,
          "y": 247
        },
        {
          "x": 731.5,
          "y": 327
        },
        {
          "x": 755.5,
          "y": 389
        },
        {
          "x": 755.5,
          "y": 437
        },
        {
          "x": 755.5,
          "y": 466
        },
        {
          "x": 755.5,
          "y": 467
        },
        {
          "x": 62.5,
          "y": 269
        },
        {
          "x": 33.5,
          "y": 354
        },
        {
          "x": 25.5,
          "y": 384
        },
        {
          "x": 27.5,
          "y": 469
        },
        {
          "x": 16.5,
          "y": 518
        },
        {
          "x": 17.5,
          "y": 537
        },
        {
          "x": 26.5,
          "y": 547
        },
        {
          "x": 60.5,
          "y": 598
        },
        {
          "x": 131.5,
          "y": 668
        },
        {
          "x": 159.5,
          "y": 696
        },
        {
          "x": 170.5,
          "y": 708
        },
        {
          "x": 264.5,
          "y": 811
        }
      ],
      "three": [],
      "one": []
    },
    {
      "player_name": "McCULLAM",
      "id": 1516871797,
      "team_id": 1516871698,
      "match_id": 1,
      "six": [
        {
          "x": 112.5,
          "y": 145
        },
        {
          "x": 49.5,
          "y": 226
        },
        {
          "x": 33.5,
          "y": 275
        },
        {
          "x": 19.5,
          "y": 316
        },
        {
          "x": 123.5,
          "y": 877
        },
        {
          "x": 367.5,
          "y": 887
        },
        {
          "x": 730.5,
          "y": 842
        },
        {
          "x": 761.5,
          "y": 834
        },
        {
          "x": 747.5,
          "y": 122
        }
      ],
      "four": [],
      "three": [],
      "one": []
    },
    {
      "player_name": "DANIEL VATTORI",
      "id": 1516871897,
      "match_id": 1,
      "team_id": 1516871698,
      "six": [],
      "four": [],
      "three": [],
      "one": [
        {
          "x": 489.5,
          "y": 502
        },
        {
          "x": 470.5,
          "y": 541
        },
        {
          "x": 416.5,
          "y": 602
        },
        {
          "x": 362.5,
          "y": 603
        },
        {
          "x": 310.5,
          "y": 585
        },
        {
          "x": 265.5,
          "y": 520
        },
        {
          "x": 282.5,
          "y": 392
        },
        {
          "x": 293.5,
          "y": 314
        },
        {
          "x": 307.5,
          "y": 282
        }
      ]
    },
    {
      "player_name": "XXX",
      "id": 1516871997,
      "match_id": 1,
      "team_id": 1516871698,
      "six": [],
      "four": [
        {
          "x": 348.5,
          "y": 28
        },
        {
          "x": 696.5,
          "y": 38
        },
        {
          "x": 722.5,
          "y": 44
        },
        {
          "x": 753.5,
          "y": 83
        },
        {
          "x": 785.5,
          "y": 151
        },
        {
          "x": 660.5,
          "y": 866
        },
        {
          "x": 572.5,
          "y": 844
        },
        {
          "x": 551.5,
          "y": 858
        },
        {
          "x": 531.5,
          "y": 868
        },
        {
          "x": 497.5,
          "y": 892
        },
        {
          "x": 49.5,
          "y": 824
        },
        {
          "x": 35.5,
          "y": 820
        },
        {
          "x": 61.5,
          "y": 708
        },
        {
          "x": 62.5,
          "y": 665
        },
        {
          "x": 77.5,
          "y": 530
        },
        {
          "x": 71.5,
          "y": 500
        },
        {
          "x": 40.5,
          "y": 399
        },
        {
          "x": 39.5,
          "y": 395
        }
      ],
      "three": [],
      "one": []
    }
  ]
}